mory/__init__.py
mory/config_loader.py
mory/conversation.py
mory/helpers.py
mory/main.py
mory/run_tests.py
mory/scan.py
mory/version.py
mory/chat/__init__.py
mory/chat/complection.py
mory/chat/functions.py
mory-0.5.0.dist-info/LICENSE
mory-0.5.0.dist-info/METADATA
mory-0.5.0.dist-info/WHEEL
mory-0.5.0.dist-info/entry_points.txt
mory-0.5.0.dist-info/top_level.txt
mory-0.5.0.dist-info/RECORD
