Metadata-Version: 2.1
Name: mory
Version: 0.5.0
Home-page: https://gitlab.com/good-day-inc/mory/
Author: Enemchy
Author-email: dzenkir@gmail.com
Classifier: Programming Language :: Python :: 3
Classifier: License :: OSI Approved :: MIT License
Classifier: Operating System :: OS Independent
Requires-Python: >=3.10
License-File: LICENSE
Requires-Dist: rich
Requires-Dist: prompt-toolkit
Requires-Dist: openai
Requires-Dist: pyyaml
Requires-Dist: colorama
Requires-Dist: tiktoken
Requires-Dist: pytest
